opschema/__init__.py
opschema/base.py
opschema/cl.py
opschema/complib.py
opschema/error.py
opschema/fgraph.py
opschema/generators.py
opschema/genlib.py
opschema/infer.py
opschema/oparg.py
opschema/predicates.py
opschema/predlib.py
opschema/procfuncs.py
opschema/redirect.py
opschema/report.py
opschema/schema.py
opschema/validate.py
opschema/version.py
opschema/ops/__init__.py
opschema/ops/tf/__init__.py
opschema/ops/tf/gather_nd.py
opschema/ops/tf/scatter_nd.py
opschema/ops/tf/nn/__init__.py
opschema/ops/tf/nn/atrous_conv2d.py
opschema/ops/tf/nn/atrous_conv2d_transpose.py
opschema/ops/tf/nn/avg_pool.py
opschema/ops/tf/nn/bias_add.py
opschema/ops/tf/nn/conv_transpose.py
opschema/ops/tf/nn/convolution.py
opschema/ops/tf/nn/depth_to_space.py
opschema/ops/tf/nn/separable_conv2d.py
opschema/ops/tf/nn/space_to_batch.py
opschema/ops/tf/nn/space_to_depth.py
opschema/ops/tf/raw_ops/LSTMBlockCell.py
opschema/ops/tf/raw_ops/__init__.py
opschema-0.2.2.dist-info/LICENSE.txt
opschema-0.2.2.dist-info/METADATA
opschema-0.2.2.dist-info/WHEEL
opschema-0.2.2.dist-info/entry_points.txt
opschema-0.2.2.dist-info/top_level.txt
opschema-0.2.2.dist-info/RECORD
