Metadata-Version: 2.1
Name: opschema
Version: 0.2.2
Summary: Define Error-checking Schemas for TensorFlow ops
Home-page: https://github.com/hrbigelow/opschema
Author: Henry Bigelow
Author-email: hrbigelow@gmail.com
License: MIT
License-File: LICENSE.txt
Requires-Dist: tensorflow
Requires-Dist: fire
